zendesk_auth/__init__.py
zendesk_auth/models.py
zendesk_auth/tests.py
zendesk_auth/urls.py
zendesk_auth/views.py
zendesk_auth/templates/zendesk_auth/zendesk_auth_passthrough.html
zendesk_django_auth-0.3.1.dist-info/LICENSE
zendesk_django_auth-0.3.1.dist-info/METADATA
zendesk_django_auth-0.3.1.dist-info/WHEEL
zendesk_django_auth-0.3.1.dist-info/top_level.txt
zendesk_django_auth-0.3.1.dist-info/RECORD
